{ "compressionlevel":-1,
 "height":5,
 "infinite":false,
 "layers":[
        {
         "data":[0, 0, 0, 0, 0, 0, 0, 0, 0, 0, 0, 0, 0, 0, 0,
            0, 0, 0, 0, 0, 0, 0, 0, 0, 0, 0, 0, 0, 0, 0,
            31, 30, 30, 24, 30, 30, 31, 24, 31, 30, 24, 30, 31, 24, 30,
            32, 32, 32, 32, 32, 32, 32, 32, 32, 32, 32, 32, 32, 32, 32,
            0, 0, 0, 0, 0, 0, 0, 0, 0, 0, 0, 0, 0, 0, 0],
         "height":5,
         "id":2,
         "name":"backsand",
         "opacity":1,
         "type":"tilelayer",
         "visible":true,
         "width":15,
         "x":0,
         "y":0
        }, 
        {
         "draworder":"topdown",
         "id":3,
         "name":"backobjs",
         "objects":[
                {
                 "gid":33,
                 "height":128,
                 "id":1,
                 "name":"",
                 "properties":[
                        {
                         "name":"moves",
                         "type":"bool",
                         "value":true
                        }],
                 "rotation":0,
                 "type":"",
                 "visible":true,
                 "width":128,
                 "x":124,
                 "y":282
                }, 
                {
                 "gid":33,
                 "height":128,
                 "id":2,
                 "name":"",
                 "properties":[
                        {
                         "name":"moves",
                         "type":"bool",
                         "value":true
                        }],
                 "rotation":0,
                 "type":"",
                 "visible":true,
                 "width":128,
                 "x":898,
                 "y":276
                }, 
                {
                 "gid":34,
                 "height":128,
                 "id":3,
                 "name":"",
                 "properties":[
                        {
                         "name":"moves",
                         "type":"bool",
                         "value":true
                        }],
                 "rotation":0,
                 "type":"",
                 "visible":true,
                 "width":128,
                 "x":1292,
                 "y":280
                }, 
                {
                 "gid":35,
                 "height":128,
                 "id":4,
                 "name":"",
                 "properties":[
                        {
                         "name":"moves",
                         "type":"bool",
                         "value":true
                        }],
                 "rotation":0,
                 "type":"",
                 "visible":true,
                 "width":128,
                 "x":520,
                 "y":274
                }, 
                {
                 "gid":37,
                 "height":128,
                 "id":5,
                 "name":"",
                 "properties":[
                        {
                         "name":"moves",
                         "type":"bool",
                         "value":false
                        }],
                 "rotation":0,
                 "type":"",
                 "visible":true,
                 "width":128,
                 "x":1804,
                 "y":272
                }, 
                {
                 "gid":38,
                 "height":128,
                 "id":6,
                 "name":"",
                 "properties":[
                        {
                         "name":"moves",
                         "type":"bool",
                         "value":false
                        }],
                 "rotation":0,
                 "type":"",
                 "visible":true,
                 "width":128,
                 "x":1356,
                 "y":290
                }, 
                {
                 "gid":39,
                 "height":128,
                 "id":7,
                 "name":"",
                 "properties":[
                        {
                         "name":"moves",
                         "type":"bool",
                         "value":false
                        }],
                 "rotation":0,
                 "type":"",
                 "visible":true,
                 "width":128,
                 "x":1244,
                 "y":286
                }, 
                {
                 "gid":41,
                 "height":128,
                 "id":8,
                 "name":"",
                 "properties":[
                        {
                         "name":"moves",
                         "type":"bool",
                         "value":true
                        }],
                 "rotation":0,
                 "type":"",
                 "visible":true,
                 "width":128,
                 "x":1428,
                 "y":290
                }, 
                {
                 "gid":42,
                 "height":128,
                 "id":9,
                 "name":"",
                 "properties":[
                        {
                         "name":"moves",
                         "type":"bool",
                         "value":true
                        }],
                 "rotation":0,
                 "type":"",
                 "visible":true,
                 "width":128,
                 "x":714,
                 "y":278
                }, 
                {
                 "gid":41,
                 "height":128,
                 "id":10,
                 "name":"",
                 "properties":[
                        {
                         "name":"moves",
                         "type":"bool",
                         "value":true
                        }],
                 "rotation":0,
                 "type":"",
                 "visible":true,
                 "width":128,
                 "x":786,
                 "y":274
                }, 
                {
                 "gid":37,
                 "height":128,
                 "id":11,
                 "name":"",
                 "properties":[
                        {
                         "name":"moves",
                         "type":"bool",
                         "value":false
                        }],
                 "rotation":0,
                 "type":"",
                 "visible":true,
                 "width":128,
                 "x":296,
                 "y":272
                }, 
                {
                 "gid":40,
                 "height":128,
                 "id":12,
                 "name":"",
                 "properties":[
                        {
                         "name":"moves",
                         "type":"bool",
                         "value":false
                        }],
                 "rotation":0,
                 "type":"",
                 "visible":true,
                 "width":128,
                 "x":1076,
                 "y":280
                }, 
                {
                 "gid":38,
                 "height":128,
                 "id":13,
                 "name":"",
                 "properties":[
                        {
                         "name":"moves",
                         "type":"bool",
                         "value":false
                        }],
                 "rotation":0,
                 "type":"",
                 "visible":true,
                 "width":128,
                 "x":358,
                 "y":268
                }, 
                {
                 "gid":38,
                 "height":128,
                 "id":14,
                 "name":"",
                 "properties":[
                        {
                         "name":"moves",
                         "type":"bool",
                         "value":false
                        }],
                 "rotation":0,
                 "type":"",
                 "visible":true,
                 "width":128,
                 "x":1650,
                 "y":286
                }, 
                {
                 "gid":41,
                 "height":128,
                 "id":15,
                 "name":"",
                 "properties":[
                        {
                         "name":"moves",
                         "type":"bool",
                         "value":true
                        }],
                 "rotation":0,
                 "type":"",
                 "visible":true,
                 "width":128,
                 "x":1716,
                 "y":272
                }],
         "opacity":1,
         "type":"objectgroup",
         "visible":true,
         "x":0,
         "y":0
        }, 
        {
         "data":[0, 0, 0, 0, 0, 0, 0, 0, 0, 0, 0, 0, 0, 0, 0,
            0, 0, 0, 0, 0, 0, 0, 0, 0, 0, 0, 0, 0, 0, 0,
            0, 0, 0, 0, 0, 0, 0, 0, 0, 0, 0, 0, 0, 0, 0,
            3, 4, 17, 18, 3, 17, 4, 4, 3, 3, 17, 20, 19, 3, 17,
            1, 1, 1, 10, 2, 1, 1, 2, 9, 10, 1, 2, 2, 1, 1],
         "height":5,
         "id":1,
         "name":"frontsand",
         "opacity":1,
         "type":"tilelayer",
         "visible":true,
         "width":15,
         "x":0,
         "y":0
        }],
 "nextlayerid":4,
 "nextobjectid":16,
 "orientation":"orthogonal",
 "renderorder":"right-down",
 "tiledversion":"1.10.2",
 "tileheight":128,
 "tilesets":[
        {
         "columns":8,
         "firstgid":1,
         "image":"spritesheet-fish1.png",
         "imageheight":512,
         "imagewidth":1024,
         "margin":0,
         "name":"spritesheet-fish1",
         "spacing":0,
         "tilecount":32,
         "tileheight":128,
         "tilewidth":128
        }, 
        {
         "columns":5,
         "firstgid":33,
         "image":"backobjects-fish1.png",
         "imageheight":256,
         "imagewidth":640,
         "margin":0,
         "name":"backobjects-fish1",
         "spacing":0,
         "tilecount":10,
         "tileheight":128,
         "tilewidth":128
        }],
 "tilewidth":128,
 "type":"map",
 "version":"1.10",
 "width":15
}